affectlog_utils/__init__.py
affectlog_utils/exceptions.py
affectlog_utils/version.py
affectlog_utils/cohort/__init__.py
affectlog_utils/cohort/cohort.py
affectlog_utils/cohort/constants.py
affectlog_utils/common/__init__.py
affectlog_utils/common/retries.py
affectlog_utils/data_processing/__init__.py
affectlog_utils/data_processing/data_processing_utils.py
affectlog_utils/dataset/__init__.py
affectlog_utils/dataset/dataset.py
affectlog_utils/models/__init__.py
affectlog_utils/models/model_utils.py
affectlog_utils/sampling/__init__.py
affectlog_utils/sampling/random_sampling.py
affectlog_utils/webservice/__init__.py
affectlog_utils/webservice/webservice.py
affectlog_utils-0.4.4.dist-info/LICENSE
affectlog_utils-0.4.4.dist-info/METADATA
affectlog_utils-0.4.4.dist-info/WHEEL
affectlog_utils-0.4.4.dist-info/top_level.txt
affectlog_utils-0.4.4.dist-info/RECORD
